dialpad/__init__.py
dialpad/async_client.py
dialpad/client.py
dialpad/py.typed
dialpad/async_resources/__init__.py
dialpad/async_resources/async_access_control_policies_resource.py
dialpad/async_resources/async_agent_status_event_subscriptions_resource.py
dialpad/async_resources/async_app_settings_resource.py
dialpad/async_resources/async_blocked_numbers_resource.py
dialpad/async_resources/async_call_center_operators_resource.py
dialpad/async_resources/async_call_centers_resource.py
dialpad/async_resources/async_call_event_subscriptions_resource.py
dialpad/async_resources/async_call_labels_resource.py
dialpad/async_resources/async_call_review_share_links_resource.py
dialpad/async_resources/async_call_routers_resource.py
dialpad/async_resources/async_callbacks_resource.py
dialpad/async_resources/async_calls_resource.py
dialpad/async_resources/async_changelog_event_subscriptions_resource.py
dialpad/async_resources/async_channels_resource.py
dialpad/async_resources/async_coaching_teams_resource.py
dialpad/async_resources/async_company_resource.py
dialpad/async_resources/async_contact_event_subscriptions_resource.py
dialpad/async_resources/async_contacts_resource.py
dialpad/async_resources/async_custom_ivrs_resource.py
dialpad/async_resources/async_departments_resource.py
dialpad/async_resources/async_fax_lines_resource.py
dialpad/async_resources/async_meeting_rooms_resource.py
dialpad/async_resources/async_meetings_resource.py
dialpad/async_resources/async_numbers_resource.py
dialpad/async_resources/async_oauth2_resource.py
dialpad/async_resources/async_offices_resource.py
dialpad/async_resources/async_recording_share_links_resource.py
dialpad/async_resources/async_rooms_resource.py
dialpad/async_resources/async_schedule_reports_resource.py
dialpad/async_resources/async_sms_event_subscriptions_resource.py
dialpad/async_resources/async_sms_resource.py
dialpad/async_resources/async_stats_resource.py
dialpad/async_resources/async_transcripts_resource.py
python_dialpad-3.1.0.dist-info/METADATA
python_dialpad-3.1.0.dist-info/WHEEL
python_dialpad-3.1.0.dist-info/entry_points.txt
python_dialpad-3.1.0.dist-info/licenses/LICENSE
python_dialpad-3.1.0.dist-info/RECORD
