Metadata-Version: 2.4
Name: python-dialpad
Version: 3.1.0
Summary: A python wrapper for the Dialpad REST API
License-File: LICENSE
Requires-Python: >=3.9
Requires-Dist: cached-property>=2.0.1
Requires-Dist: httpx>=0.28.1
Requires-Dist: requests>=2.28.0
